{"first_name":"Worthington","last_name":"Eberdt","email":"weberdt0@merriam-webster.com","gender":"Male","phone_number":"875-434-4698","address":"68 Almo Hill","address_line_2":"Room 1262","city":"Shizi","Country":"China"}
{"first_name":"Loralyn","last_name":"Pache","email":"lpache1@tripod.com","gender":"Female","phone_number":"800-741-1785","address":"7436 Straubel Terrace","address_line_2":"PO Box 67934","city":"Chitose","postal_code":"990-0812","Country":"Japan"}
{"first_name":"Aylmer","last_name":"Calderhead","email":"acalderhead2@wikipedia.org","gender":"Male","phone_number":"360-547-3602","address":"94 Westend Junction","address_line_2":"Room 524","city":"Licheng","Country":"China"}
{"first_name":"Eric","last_name":"Gingell","email":"egingell3@senate.gov","gender":"Male","phone_number":"846-792-1522","address":"9209 Washington Lane","address_line_2":"PO Box 32029","city":"Paradela","postal_code":"4785-231","Province":"Porto","Country":"Portugal"}
{"first_name":"Erma","last_name":"Spain","email":"espain4@ycombinator.com","gender":"Female","phone_number":"301-491-7772","address":"40 Fair Oaks Junction","address_line_2":"3rd Floor","city":"Hougaoshizhuang","Country":"China"}
{"first_name":"Jarred","last_name":"Giovani","email":"jgiovani5@wikimedia.org","gender":"Male","phone_number":"454-703-0816","address":"8374 Kennedy Place","address_line_2":"Room 1465","city":"Monastir","Country":"Tunisia"}
{"first_name":"Brianne","last_name":"Mowlam","email":"bmowlam6@dyndns.org","gender":"Female","phone_number":"736-228-5124","address":"242 Steensland Trail","address_line_2":"8th Floor","city":"Leping","Country":"China"}
{"first_name":"Kelsi","last_name":"Tumilty","email":"ktumilty7@fema.gov","gender":"Female","phone_number":"153-365-0477","address":"4 South Junction","address_line_2":"15th Floor","city":"Zhaitou","Country":"China"}
{"first_name":"Angeli","last_name":"Wibrew","email":"awibrew8@gnu.org","gender":"Male","phone_number":"667-639-8239","address":"4 Texas Pass","address_line_2":"Suite 69","city":"Chernogorsk","postal_code":"655138","Country":"Russia"}
{"first_name":"Marylou","last_name":"Edgin","email":"medgin9@networkadvertising.org","gender":"Female","phone_number":"110-669-7339","address":"20120 Arapahoe Court","address_line_2":"PO Box 72347","city":"Vrbas","Country":"Serbia"}
{"first_name":"Nicolea","last_name":"Cleworth","email":"nclewortha@issuu.com","gender":"Female","phone_number":"408-190-7846","address":"1103 Drewry Circle","address_line_2":"PO Box 41627","city":"San Jose","postal_code":"95138","Province":"California","Country":"United States"}
{"first_name":"Alethea","last_name":"Ruecastle","email":"aruecastleb@cisco.com","gender":"Female","phone_number":"512-392-9806","address":"0853 Hauk Pass","address_line_2":"Suite 38","city":"Austin","postal_code":"78726","Province":"Texas","Country":"United States"}
{"first_name":"Gardy","last_name":"Middle","email":"gmiddlec@paginegialle.it","gender":"Male","phone_number":"289-543-7343","address":"7513 Basil Way","address_line_2":"Suite 81","city":"Leuwibuleud","Country":"Indonesia"}
{"first_name":"Jolie","last_name":"Butt Gow","email":"jbuttgowd@cnbc.com","gender":"Bigender","phone_number":"316-600-0883","address":"96 Butternut Way","address_line_2":"Room 280","city":"Riit","Country":"Indonesia"}
{"first_name":"Marice","last_name":"O' Ronan","email":"moronane@nps.gov","gender":"Female","phone_number":"670-396-6396","address":"235 Haas Street","address_line_2":"Apt 1101","city":"Lundo","Country":"Indonesia"}
{"first_name":"Theo","last_name":"Esom","email":"tesomf@ebay.co.uk","gender":"Female","phone_number":"579-957-3943","address":"4 Mcbride Crossing","address_line_2":"PO Box 19490","city":"Shanhe","Country":"China"}
{"first_name":"Erskine","last_name":"Yousef","email":"eyousefg@telegraph.co.uk","gender":"Male","phone_number":"404-692-7150","address":"97221 Summit Place","address_line_2":"Suite 20","city":"Atlanta","postal_code":"30343","Province":"Georgia","Country":"United States"}
{"first_name":"Cherry","last_name":"Duce","email":"cduceh@addthis.com","gender":"Female","phone_number":"280-567-8386","address":"654 Duke Road","address_line_2":"Suite 68","city":"Nice","postal_code":"06357 CEDEX 4","Province":"Provence-Alpes-Côte d'Azur","Country":"France"}
{"first_name":"Urbano","last_name":"Zoellner","email":"uzoellneri@patch.com","gender":"Male","phone_number":"134-223-7289","address":"02395 Petterle Pass","address_line_2":"Room 1139","city":"Aparecida","postal_code":"12570-000","Country":"Brazil"}
{"first_name":"Reg","last_name":"Mullinger","email":"rmullingerj@omniture.com","gender":"Male","phone_number":"274-799-3370","address":"25670 Westport Point","address_line_2":"PO Box 31644","city":"Chitral","postal_code":"17200","Country":"Pakistan"}
{"first_name":"Dael","last_name":"Tabbernor","email":"dtabbernork@nih.gov","gender":"Male","phone_number":"367-379-2770","address":"04 Derek Alley","address_line_2":"Apt 654","city":"Glagahdowo","Country":"Indonesia"}
{"first_name":"Mathian","last_name":"Torbet","email":"mtorbetl@joomla.org","gender":"Male","phone_number":"891-659-6426","address":"1100 Pleasure Road","address_line_2":"Room 1576","city":"Uenohara","postal_code":"981-4327","Country":"Japan"}
{"first_name":"Genevieve","last_name":"Beaument","email":"gbeaumentm@si.edu","gender":"Female","phone_number":"755-459-3000","address":"0 Garrison Trail","address_line_2":"PO Box 73275","city":"Divinópolis","postal_code":"35500-000","Country":"Brazil"}
{"first_name":"Nevsa","last_name":"Marshal","email":"nmarshaln@senate.gov","gender":"Female","phone_number":"721-241-0527","address":"53 Acker Way","address_line_2":"Apt 85","city":"Lümeng","Country":"China"}
{"first_name":"Mair","last_name":"Oki","email":"mokio@cpanel.net","gender":"Female","phone_number":"619-553-4123","address":"65 Straubel Drive","address_line_2":"15th Floor","city":"Văn Điển","Country":"Vietnam"}
{"first_name":"Malissa","last_name":"Jupe","email":"mjupep@google.nl","gender":"Genderqueer","phone_number":"762-152-7712","address":"853 Kim Drive","address_line_2":"PO Box 826","city":"Chao","Country":"Peru"}
{"first_name":"Evered","last_name":"Brownsey","email":"ebrownseyq@deliciousdays.com","gender":"Male","phone_number":"314-145-7959","address":"9431 Shoshone Trail","address_line_2":"Room 1276","city":"Buray","postal_code":"5020","Country":"Philippines"}
{"first_name":"Robbert","last_name":"Fuge","email":"rfuger@harvard.edu","gender":"Male","phone_number":"109-443-1320","address":"19804 Rieder Trail","address_line_2":"Room 1907","city":"Menglie","Country":"China"}
{"first_name":"Virgie","last_name":"Leney","email":"vleneys@irs.gov","gender":"Male","phone_number":"900-957-7298","address":"90375 Doe Crossing Junction","address_line_2":"Room 1313","city":"Sharīfābād","Country":"Iran"}
{"first_name":"Ted","last_name":"Gilbeart","email":"tgilbeartt@tripod.com","gender":"Female","phone_number":"792-755-0640","address":"2869 Stone Corner Place","address_line_2":"Suite 93","city":"Maromitsa","postal_code":"613840","Country":"Russia"}
{"first_name":"Verna","last_name":"Roobottom","email":"vroobottomu@hc360.com","gender":"Female","phone_number":"868-120-0667","address":"4 Lotheville Alley","address_line_2":"Room 478","city":"Shikeng","Country":"China"}
{"first_name":"Joann","last_name":"Shillabear","email":"jshillabearv@pbs.org","gender":"Female","phone_number":"333-447-6759","address":"3 Dahle Parkway","address_line_2":"3rd Floor","city":"São João del Rei","postal_code":"36300-000","Country":"Brazil"}
{"first_name":"Crysta","last_name":"Burchell","email":"cburchellw@bandcamp.com","gender":"Bigender","phone_number":"559-925-3713","address":"622 Lawn Place","address_line_2":"Suite 8","city":"Henghe","Country":"China"}
{"first_name":"Marla","last_name":"Hebner","email":"mhebnerx@cbsnews.com","gender":"Female","phone_number":"316-404-1725","address":"7943 Manufacturers Hill","address_line_2":"PO Box 23304","city":"Catabola","Country":"Angola"}
{"first_name":"Blaine","last_name":"Huckerby","email":"bhuckerbyy@wikimedia.org","gender":"Genderqueer","phone_number":"528-576-8390","address":"0786 Straubel Hill","address_line_2":"PO Box 88163","city":"Mont-Laurier","postal_code":"J9L","Province":"Québec","Country":"Canada"}
{"first_name":"Annabela","last_name":"Coakley","email":"acoakleyz@ft.com","gender":"Genderqueer","phone_number":"820-614-9736","address":"8 Pearson Circle","address_line_2":"Apt 517","city":"San Remigio","postal_code":"6011","Country":"Philippines"}
{"first_name":"Susie","last_name":"Marushak","email":"smarushak10@facebook.com","gender":"Female","phone_number":"540-628-4586","address":"88 Bunting Way","address_line_2":"PO Box 16385","city":"Honggang","Country":"China"}
{"first_name":"Latrena","last_name":"Rea","email":"lrea11@usda.gov","gender":"Female","phone_number":"241-753-4401","address":"8 Lillian Road","address_line_2":"Apt 657","city":"Ust’-Labinsk","postal_code":"385321","Country":"Russia"}
{"first_name":"Clementina","last_name":"Leavens","email":"cleavens12@cisco.com","gender":"Genderqueer","phone_number":"717-187-3904","address":"6865 Jackson Park","address_line_2":"Room 1451","city":"Huagai","Country":"China"}
{"first_name":"Leoine","last_name":"Mesias","email":"lmesias13@fema.gov","gender":"Female","phone_number":"682-523-3370","address":"09 Caliangt Plaza","address_line_2":"PO Box 93227","city":"Boa Esperança","postal_code":"87390-000","Country":"Brazil"}
{"first_name":"Kahaleel","last_name":"Vasiliu","email":"kvasiliu14@paypal.com","gender":"Male","phone_number":"201-370-6400","address":"27 Express Parkway","address_line_2":"PO Box 28932","city":"Noshiro","postal_code":"921-8804","Country":"Japan"}
{"first_name":"Nate","last_name":"Bonhan","email":"nbonhan15@simplemachines.org","gender":"Male","phone_number":"861-599-9396","address":"51704 Knutson Park","address_line_2":"PO Box 5358","city":"Caieiras","postal_code":"07700-000","Country":"Brazil"}
{"first_name":"Griselda","last_name":"Pattlel","email":"gpattlel16@acquirethisname.com","gender":"Female","phone_number":"480-960-5297","address":"51 Ohio Point","address_line_2":"Apt 275","city":"Město Libavá","postal_code":"783 06","Country":"Czech Republic"}
{"first_name":"Markus","last_name":"Mallabone","email":"mmallabone17@xinhuanet.com","gender":"Male","phone_number":"616-455-0423","address":"07692 Hovde Street","address_line_2":"Suite 26","city":"Riolândia","postal_code":"15495-000","Country":"Brazil"}
{"first_name":"Cecil","last_name":"Dowley","email":"cdowley18@merriam-webster.com","gender":"Female","phone_number":"249-854-9741","address":"47583 Ryan Drive","address_line_2":"Apt 195","city":"Campo Alegre","postal_code":"89294-000","Country":"Brazil"}
{"first_name":"Alysia","last_name":"Kinsley","email":"akinsley19@photobucket.com","gender":"Female","phone_number":"192-592-7185","address":"6 Oriole Way","address_line_2":"20th Floor","city":"Osh","Country":"Kyrgyzstan"}
{"first_name":"Allx","last_name":"Bohlens","email":"abohlens1a@salon.com","gender":"Female","phone_number":"432-855-1251","address":"0 Lakewood Hill","address_line_2":"Suite 99","city":"Saint-Priest","postal_code":"69794 CEDEX","Province":"Rhône-Alpes","Country":"France"}
{"first_name":"Glen","last_name":"Buzine","email":"gbuzine1b@amazon.co.uk","gender":"Male","phone_number":"154-919-0475","address":"46524 Pawling Terrace","address_line_2":"Suite 62","city":"Banjar Batuaji Kaja","Country":"Indonesia"}
{"first_name":"Thebault","last_name":"Dack","email":"tdack1c@mlb.com","gender":"Male","phone_number":"294-420-3884","address":"940 Texas Road","address_line_2":"2nd Floor","city":"Khiliomódhi","Country":"Greece"}
{"first_name":"Bernita","last_name":"Turford","email":"bturford1d@instagram.com","gender":"Female","phone_number":"230-868-6754","address":"029 Meadow Ridge Road","address_line_2":"Suite 59","city":"Akure","Country":"Nigeria"}
{"first_name":"Allianora","last_name":"Schmuhl","email":"aschmuhl1e@baidu.com","gender":"Female","phone_number":"317-206-2695","address":"83126 Hallows Street","address_line_2":"Suite 5","city":"Kuala Terengganu","postal_code":"20916","Province":"Terengganu","Country":"Malaysia"}
{"first_name":"Jessika","last_name":"Hasling","email":"jhasling1f@bluehost.com","gender":"Agender","phone_number":"229-215-3163","address":"99 Lawn Park","address_line_2":"Suite 36","city":"Arras","postal_code":"62025 CEDEX","Province":"Nord-Pas-de-Calais","Country":"France"}
{"first_name":"Jo-anne","last_name":"Bunstone","email":"jbunstone1g@networkadvertising.org","gender":"Female","phone_number":"721-598-9235","address":"4911 Barby Pass","address_line_2":"Suite 45","city":"Drybin","Country":"Belarus"}
{"first_name":"Aggie","last_name":"Saintsbury","email":"asaintsbury1h@com.com","gender":"Female","phone_number":"698-480-9909","address":"6309 Haas Avenue","address_line_2":"10th Floor","city":"Shihuiyao","Country":"China"}
{"first_name":"Darb","last_name":"Levison","email":"dlevison1i@edublogs.org","gender":"Male","phone_number":"924-169-4953","address":"4679 Northfield Road","address_line_2":"PO Box 56058","city":"Pentre","postal_code":"SY4","Province":"Wales","Country":"United Kingdom"}
{"first_name":"Temple","last_name":"Youster","email":"tyouster1j@simplemachines.org","gender":"Male","phone_number":"914-561-9945","address":"557 Barnett Road","address_line_2":"PO Box 20599","city":"Ambarawa","Country":"Indonesia"}
{"first_name":"Morris","last_name":"Minney","email":"mminney1k@uol.com.br","gender":"Male","phone_number":"538-516-0306","address":"24 Manitowish Point","address_line_2":"Apt 1269","city":"Khlong Yai","postal_code":"23110","Country":"Thailand"}
{"first_name":"Car","last_name":"Blare","email":"cblare1l@ifeng.com","gender":"Male","phone_number":"157-890-5708","address":"4 Prairieview Avenue","address_line_2":"Suite 18","city":"Villa Atamisqui","postal_code":"4317","Country":"Argentina"}
{"first_name":"Carmon","last_name":"Haill","email":"chaill1m@about.me","gender":"Female","phone_number":"334-675-7244","address":"53470 Stephen Trail","address_line_2":"3rd Floor","city":"Benguela","Country":"Angola"}
{"first_name":"Pietrek","last_name":"Coultard","email":"pcoultard1n@github.com","gender":"Male","phone_number":"575-482-2999","address":"6 Hollow Ridge Pass","address_line_2":"PO Box 63999","city":"Guiset East","postal_code":"2434","Country":"Philippines"}
{"first_name":"Charlena","last_name":"Bartels-Ellis","email":"cbartelsellis1o@patch.com","gender":"Female","phone_number":"139-223-1362","address":"870 Moulton Way","address_line_2":"Room 1066","city":"Liufeng","Country":"China"}
{"first_name":"Nikki","last_name":"Gillivrie","email":"ngillivrie1p@va.gov","gender":"Male","phone_number":"709-525-9966","address":"8 Victoria Point","address_line_2":"18th Floor","city":"Novais","postal_code":"4765-122","Province":"Braga","Country":"Portugal"}
{"first_name":"Domenico","last_name":"Oakeshott","email":"doakeshott1q@cbsnews.com","gender":"Male","phone_number":"630-506-7834","address":"3 Oak Way","address_line_2":"PO Box 71592","city":"Lewotukan","Country":"Indonesia"}
{"first_name":"Dalton","last_name":"Elloit","email":"delloit1r@hugedomains.com","gender":"Bigender","phone_number":"808-571-5745","address":"664 Carberry Place","address_line_2":"Apt 355","city":"Honolulu","postal_code":"96805","Province":"Hawaii","Country":"United States"}
{"first_name":"Trudi","last_name":"Barszczewski","email":"tbarszczewski1s@shareasale.com","gender":"Bigender","phone_number":"686-218-8365","address":"1 Bunker Hill Pass","address_line_2":"Suite 30","city":"McKinley","postal_code":"6214","Country":"Philippines"}
{"first_name":"Petra","last_name":"Iglesia","email":"piglesia1t@symantec.com","gender":"Female","phone_number":"445-641-5885","address":"62548 Pearson Place","address_line_2":"17th Floor","city":"Mingcheng","Country":"China"}
{"first_name":"Sloan","last_name":"Cargon","email":"scargon1u@washington.edu","gender":"Male","phone_number":"521-263-5556","address":"29 Paget Terrace","address_line_2":"Room 1135","city":"Banjar Jagasatru","Country":"Indonesia"}
{"first_name":"Fawne","last_name":"Bush","email":"fbush1v@g.co","gender":"Female","phone_number":"891-114-6520","address":"7 Dunning Circle","address_line_2":"Suite 3","city":"Santa Rosa","Country":"Peru"}
{"first_name":"Guenevere","last_name":"Kitchingham","email":"gkitchingham1w@columbia.edu","gender":"Female","phone_number":"785-899-6238","address":"9 Northwestern Terrace","address_line_2":"Apt 431","city":"Stockholm","postal_code":"103 70","Province":"Stockholm","Country":"Sweden"}
{"first_name":"Sasha","last_name":"Rown","email":"srown1x@wired.com","gender":"Male","phone_number":"973-310-7498","address":"3 Harbort Way","address_line_2":"Room 1132","city":"Kamensk-Shakhtinskiy","postal_code":"396458","Country":"Russia"}
{"first_name":"Mark","last_name":"Gabotti","email":"mgabotti1y@flickr.com","gender":"Male","phone_number":"992-428-5707","address":"581 Hintze Avenue","address_line_2":"10th Floor","city":"Chotepe","Country":"Honduras"}
{"first_name":"Niels","last_name":"Raulston","email":"nraulston1z@hexun.com","gender":"Male","phone_number":"271-806-8222","address":"086 Brickson Park Alley","address_line_2":"Apt 157","city":"San Marcos","Country":"Peru"}
{"first_name":"Andreas","last_name":"Balser","email":"abalser20@csmonitor.com","gender":"Male","phone_number":"613-984-3079","address":"6001 Pierstorff Pass","address_line_2":"Room 1766","city":"Pristen’","postal_code":"306205","Country":"Russia"}
{"first_name":"Ilse","last_name":"Di Bernardo","email":"idibernardo21@icq.com","gender":"Female","phone_number":"368-224-5947","address":"00228 Susan Alley","address_line_2":"16th Floor","city":"Železný Brod","postal_code":"468 22","Country":"Czech Republic"}
{"first_name":"Colan","last_name":"Sciacovelli","email":"csciacovelli22@biglobe.ne.jp","gender":"Male","phone_number":"367-435-9723","address":"70 New Castle Park","address_line_2":"Apt 239","city":"Bamencheng","Country":"China"}
{"first_name":"Lindi","last_name":"Kinze","email":"lkinze23@guardian.co.uk","gender":"Female","phone_number":"756-482-4054","address":"722 Lotheville Court","address_line_2":"PO Box 96141","city":"Helsingborg","postal_code":"254 62","Province":"Skåne","Country":"Sweden"}
{"first_name":"Anton","last_name":"Yewdall","email":"ayewdall24@amazonaws.com","gender":"Male","phone_number":"835-300-6376","address":"77 Brentwood Center","address_line_2":"Apt 1920","city":"Yanqian","Country":"China"}
{"first_name":"Ellie","last_name":"Eckly","email":"eeckly25@dot.gov","gender":"Female","phone_number":"590-563-6525","address":"6040 Bonner Street","address_line_2":"Room 561","city":"Kamionka","postal_code":"21-132","Country":"Poland"}
{"first_name":"Cassandry","last_name":"Fildery","email":"cfildery26@ca.gov","gender":"Female","phone_number":"205-801-9521","address":"7281 Kropf Court","address_line_2":"Suite 58","city":"Sierpc","postal_code":"09-200","Country":"Poland"}
{"first_name":"Kathryne","last_name":"Odger","email":"kodger27@netvibes.com","gender":"Female","phone_number":"418-129-9479","address":"946 Trailsway Terrace","address_line_2":"Suite 14","city":"Senj","postal_code":"53270","Country":"Croatia"}
{"first_name":"Moll","last_name":"Rameau","email":"mrameau28@goo.gl","gender":"Female","phone_number":"535-807-1441","address":"5 Rusk Place","address_line_2":"Suite 58","city":"Trindade","postal_code":"56250-000","Country":"Brazil"}
{"first_name":"Kandy","last_name":"Swanwick","email":"kswanwick29@samsung.com","gender":"Female","phone_number":"315-935-2986","address":"0855 Hallows Crossing","address_line_2":"Room 1369","city":"Naushki","postal_code":"671820","Country":"Russia"}
{"first_name":"Gerhardine","last_name":"Spensly","email":"gspensly2a@timesonline.co.uk","gender":"Female","phone_number":"438-767-0098","address":"8 Melby Junction","address_line_2":"3rd Floor","city":"Villa Dolores","postal_code":"5870","Country":"Argentina"}
{"first_name":"Alf","last_name":"Cornell","email":"acornell2b@is.gd","gender":"Male","phone_number":"600-973-2260","address":"106 Birchwood Pass","address_line_2":"Room 1408","city":"Takai","Country":"Nigeria"}
{"first_name":"Ignace","last_name":"Mell","email":"imell2c@webeden.co.uk","gender":"Male","phone_number":"517-391-9842","address":"49 Glacier Hill Pass","address_line_2":"Room 594","city":"Uubulan","Country":"Mongolia"}
{"first_name":"Nickolai","last_name":"Oxteby","email":"noxteby2d@wikispaces.com","gender":"Male","phone_number":"295-158-5716","address":"746 Kedzie Circle","address_line_2":"PO Box 13427","city":"Mahaddayweyne","Country":"Somalia"}
{"first_name":"Dun","last_name":"Hachette","email":"dhachette2e@craigslist.org","gender":"Polygender","phone_number":"934-236-8117","address":"9124 Pepper Wood Avenue","address_line_2":"Suite 89","city":"Shenji","Country":"China"}
{"first_name":"Liz","last_name":"Mosedall","email":"lmosedall2f@ibm.com","gender":"Female","phone_number":"583-141-3749","address":"4 Waubesa Point","address_line_2":"PO Box 79549","city":"Pondokunyur","Country":"Indonesia"}
{"first_name":"Ginger","last_name":"Cuckson","email":"gcuckson2g@unicef.org","gender":"Female","phone_number":"845-791-0992","address":"8193 Lukken Way","address_line_2":"11th Floor","city":"Una","postal_code":"45690-000","Country":"Brazil"}
{"first_name":"Camille","last_name":"Keenor","email":"ckeenor2h@kickstarter.com","gender":"Female","phone_number":"979-332-0757","address":"539 Maywood Point","address_line_2":"Apt 955","city":"Butha-Buthe","Country":"Lesotho"}
{"first_name":"Pepe","last_name":"Shales","email":"pshales2i@cornell.edu","gender":"Male","phone_number":"999-287-3336","address":"80983 Sauthoff Court","address_line_2":"Apt 581","city":"Makabe","postal_code":"901-0336","Country":"Japan"}
{"first_name":"Aymer","last_name":"Enderby","email":"aenderby2j@miibeian.gov.cn","gender":"Genderqueer","phone_number":"397-799-3341","address":"68 Dennis Hill","address_line_2":"Apt 1925","city":"Carolina","postal_code":"65980-000","Country":"Brazil"}
{"first_name":"Eadmund","last_name":"Verrell","email":"everrell2k@google.com.au","gender":"Male","phone_number":"536-411-7773","address":"8 Pennsylvania Road","address_line_2":"Room 1331","city":"Xicheng","Country":"China"}
{"first_name":"Randene","last_name":"Jozef","email":"rjozef2l@about.com","gender":"Female","phone_number":"783-145-3950","address":"17562 Sachs Drive","address_line_2":"Suite 8","city":"Colonia Wanda","postal_code":"3376","Country":"Argentina"}
{"first_name":"Lilas","last_name":"Raysdale","email":"lraysdale2m@nifty.com","gender":"Female","phone_number":"778-369-7993","address":"9497 Boyd Parkway","address_line_2":"PO Box 27094","city":"Seremban","postal_code":"70504","Province":"Negeri Sembilan","Country":"Malaysia"}
{"first_name":"Keelby","last_name":"Hawkey","email":"khawkey2n@ebay.com","gender":"Male","phone_number":"114-526-0339","address":"3031 New Castle Center","address_line_2":"Suite 96","city":"Itapira","postal_code":"13970-000","Country":"Brazil"}
{"first_name":"Prue","last_name":"Tapscott","email":"ptapscott2o@ebay.co.uk","gender":"Genderfluid","phone_number":"239-484-0526","address":"7831 School Crossing","address_line_2":"PO Box 23175","city":"Angra dos Reis","postal_code":"23900-000","Country":"Brazil"}
{"first_name":"Celie","last_name":"Banishevitz","email":"cbanishevitz2p@taobao.com","gender":"Female","phone_number":"850-749-7032","address":"05832 Monument Center","address_line_2":"PO Box 78851","city":"Jedung","Country":"Indonesia"}
{"first_name":"Karlis","last_name":"Firby","email":"kfirby2q@un.org","gender":"Male","phone_number":"586-355-3924","address":"1681 Green Alley","address_line_2":"2nd Floor","city":"Łapsze Niżne","postal_code":"34-442","Country":"Poland"}
{"first_name":"Newton","last_name":"Cayser","email":"ncayser2r@cbsnews.com","gender":"Male","phone_number":"539-301-0914","address":"647 Manley Lane","address_line_2":"Room 1922","city":"Hantsavichy","Country":"Belarus"}